sqs_java_messaging/__init__.py
sqs_java_messaging/client.py
sqs_java_messaging/constants.py
sqs_java_messaging/message.py
sqs_java_messaging/resource.py
sqs_java_messaging-0.0.1.dist-info/LICENSE
sqs_java_messaging-0.0.1.dist-info/METADATA
sqs_java_messaging-0.0.1.dist-info/WHEEL
sqs_java_messaging-0.0.1.dist-info/top_level.txt
sqs_java_messaging-0.0.1.dist-info/RECORD
