Metadata-Version: 2.1
Name: sqs-java-messaging
Version: 0.0.1
Summary: Implements SQS JMS protocol mirroring amazon-sqs-java-messaging-lib
Home-page: https://github.com/QuiNovas/sqs-java-messaging
Author: Joseph Wortmann
Author-email: jwortmann@quinovas.com
License: Apache 2.0
Platform: UNKNOWN
Classifier: Development Status :: 4 - Beta
Classifier: Intended Audience :: Developers
Classifier: License :: OSI Approved :: Apache Software License
Classifier: Programming Language :: Python :: 3.8
